{"Add":["add","circle","include","invite","plus"],"AddCircle":["add","circle","include","invite","plus"],"AddCircleOutline":["add","circle","include","invite","outline","plus"],"AddCircleSharp":["add","circle","include","invite","plus","sharp"],"AddOutline":["add","outline"],"AddSharp":["add","circle","include","invite","plus","sharp"],"Airplane":["airplane","plane"],"AirplaneOutline":["airplane","outline","plane"],"AirplaneSharp":["airplane","plane","sharp"],"Alarm":["alarm","clock","time"],"AlarmOutline":["alarm","clock","outline","time"],"AlarmSharp":["alarm","clock","sharp","time"],"Albums":["albums","boxes","slides","square"],"AlbumsOutline":["albums","boxes","outline","slides","square"],"AlbumsSharp":["albums","boxes","sharp","slides","square"],"Alert":["!","alert","attention","exclamation","notice","warning"],"AlertCircle":["!","alert","attention","circle","exclamation","notice","warning"],"AlertCircleOutline":["!","alert","attention","circle","exclamation","notice","outline","warning"],"AlertCircleSharp":["!","alert","attention","circle","exclamation","notice","sharp","warning"],"AlertOutline":["alert","outline"],"AlertSharp":["!","alert","attention","exclamation","notice","sharp","warning"],"AmericanFootball":["american","football"],"AmericanFootballOutline":["american","football","outline"],"AmericanFootballSharp":["american","football","sharp"],"Analytics":["analytics","data","metrics","track"],"AnalyticsOutline":["analytics","data","metrics","outline","track"],"AnalyticsSharp":["analytics","data","metrics","sharp","track"],"Aperture":["aperture","dark","images","levels","light","settings"],"ApertureOutline":["aperture","dark","images","levels","light","outline","settings"],"ApertureSharp":["aperture","dark","images","levels","light","settings","sharp"],"Apps":["applications","apps"],"AppsOutline":["applications","apps","outline"],"AppsSharp":["applications","apps","sharp"],"Archive":["archive","email"],"ArchiveOutline":["archive","email","outline"],"ArchiveSharp":["archive","email","sharp"],"ArrowBack":["arrow","back","chevron","navigation"],"ArrowBackCircle":["arrow","back","chevron","circle","navigation"],"ArrowBackCircleOutline":["arrow","back","chevron","circle","navigation","outline"],"ArrowBackCircleSharp":["arrow","back","chevron","circle","navigation","sharp"],"ArrowBackOutline":["arrow","back","outline"],"ArrowBackSharp":["arrow","back","chevron","navigation","sharp"],"ArrowDown":["arrow","chevron","down"],"ArrowDownCircle":["arrow","chevron","circle","down"],"ArrowDownCircleOutline":["arrow","chevron","circle","down","outline"],"ArrowDownCircleSharp":["arrow","chevron","circle","down","sharp"],"ArrowDownOutline":["arrow","down","outline"],"ArrowDownSharp":["arrow","chevron","down","sharp"],"ArrowForward":["arrow","chevron","forward","navigation"],"ArrowForwardCircle":["arrow","chevron","circle","forward","navigation"],"ArrowForwardCircleOutline":["arrow","chevron","circle","forward","navigation","outline"],"ArrowForwardCircleSharp":["arrow","chevron","circle","forward","navigation","sharp"],"ArrowForwardOutline":["arrow","forward","outline"],"ArrowForwardSharp":["arrow","chevron","forward","navigation","sharp"],"ArrowRedo":["arrow","redo"],"ArrowRedoCircle":["arrow","circle","redo"],"ArrowRedoCircleOutline":["arrow","circle","outline","redo"],"ArrowRedoCircleSharp":["arrow","circle","redo","sharp"],"ArrowRedoOutline":["arrow","outline","redo"],"ArrowRedoSharp":["arrow","redo","sharp"],"ArrowUndo":["arrow","undo"],"ArrowUndoCircle":["arrow","circle","undo"],"ArrowUndoCircleOutline":["arrow","circle","outline","undo"],"ArrowUndoCircleSharp":["arrow","circle","sharp","undo"],"ArrowUndoOutline":["arrow","outline","undo"],"ArrowUndoSharp":["arrow","sharp","undo"],"ArrowUp":["arrow","chevron","up"],"ArrowUpCircle":["arrow","chevron","circle","up"],"ArrowUpCircleOutline":["arrow","chevron","circle","outline","up"],"ArrowUpCircleSharp":["arrow","chevron","circle","sharp","up"],"ArrowUpOutline":["arrow","outline","up"],"ArrowUpSharp":["arrow","chevron","sharp","up"],"At":["@","at"],"AtCircle":["@","at","circle"],"AtCircleOutline":["@","at","circle","outline"],"AtCircleSharp":["@","at","circle","sharp"],"AtOutline":["at","outline"],"AtSharp":["@","at","sharp"],"Attach":["attach"],"AttachOutline":["attach","outline"],"AttachSharp":["attach","sharp"],"Backspace":["backspace"],"BackspaceOutline":["backspace","outline"],"BackspaceSharp":["backspace","sharp"],"Bandage":["bandage"],"BandageOutline":["bandage","outline"],"BandageSharp":["bandage","sharp"],"BarChart":["bar","chart"],"BarChartOutline":["bar","chart","outline"],"BarChartSharp":["bar","chart","sharp"],"Barbell":["barbell"],"BarbellOutline":["barbell","outline"],"BarbellSharp":["barbell","sharp"],"Barcode":["barcode","camera","reader"],"BarcodeOutline":["barcode","camera","outline","reader"],"BarcodeSharp":["barcode","camera","reader","sharp"],"Baseball":["baseball"],"BaseballOutline":["baseball","outline"],"BaseballSharp":["baseball","sharp"],"Basket":["basket"],"BasketOutline":["basket","outline"],"BasketSharp":["basket","sharp"],"Basketball":["basketball"],"BasketballOutline":["basketball","outline"],"BasketballSharp":["basketball","sharp"],"BatteryCharging":["battery","charging"],"BatteryChargingOutline":["battery","charging","outline"],"BatteryChargingSharp":["battery","charging","sharp"],"BatteryDead":["battery","dead"],"BatteryDeadOutline":["battery","dead","outline"],"BatteryDeadSharp":["battery","dead","sharp"],"BatteryFull":["battery","full"],"BatteryFullOutline":["battery","full","outline"],"BatteryFullSharp":["battery","full","sharp"],"BatteryHalf":["battery","half"],"BatteryHalfOutline":["battery","half","outline"],"BatteryHalfSharp":["battery","half","sharp"],"Beaker":["beaker","flask","mixture","potion"],"BeakerOutline":["beaker","flask","mixture","outline","potion"],"BeakerSharp":["beaker","flask","mixture","potion","sharp"],"Bed":["bed","hotel","sleep"],"BedOutline":["bed","hotel","outline","sleep"],"BedSharp":["bed","hotel","sharp","sleep"],"Beer":["beer","drink","eat","food"],"BeerOutline":["beer","drink","eat","food","outline"],"BeerSharp":["beer","drink","eat","food","sharp"],"Bicycle":["bicycle"],"BicycleOutline":["bicycle","outline"],"BicycleSharp":["bicycle","sharp"],"Bluetooth":["bluetooth","cloud","connection"],"BluetoothOutline":["bluetooth","cloud","connection","outline"],"BluetoothSharp":["bluetooth","cloud","connection","sharp"],"Boat":["boat"],"BoatOutline":["boat","outline"],"BoatSharp":["boat","sharp"],"Body":["body"],"BodyOutline":["body","outline"],"BodySharp":["body","sharp"],"Bonfire":["bonfire","heat","hot"],"BonfireOutline":["bonfire","heat","hot","outline"],"BonfireSharp":["bonfire","heat","hot","sharp"],"Book":["book","read"],"BookOutline":["book","outline","read"],"BookSharp":["book","read","sharp"],"Bookmark":["bookmark","favorite","save","tag"],"BookmarkOutline":["bookmark","favorite","outline","save","tag"],"BookmarkSharp":["bookmark","favorite","save","sharp","tag"],"Bookmarks":["bookmarks","favorite"],"BookmarksOutline":["bookmarks","favorite","outline"],"BookmarksSharp":["bookmarks","favorite","sharp"],"Briefcase":["briefcase","folder","organize"],"BriefcaseOutline":["briefcase","folder","organize","outline"],"BriefcaseSharp":["briefcase","folder","organize","sharp"],"Browsers":["browsers","square"],"BrowsersOutline":["browsers","outline","square"],"BrowsersSharp":["browsers","sharp","square"],"Brush":["brush"],"BrushOutline":["brush","outline"],"BrushSharp":["brush","sharp"],"Bug":["bug","develop","error","hacker","program"],"BugOutline":["bug","develop","error","hacker","outline","program"],"BugSharp":["bug","develop","error","hacker","program","sharp"],"Build":["build"],"BuildOutline":["build","outline"],"BuildSharp":["build","sharp"],"Bulb":["bulb"],"BulbOutline":["bulb","outline"],"BulbSharp":["bulb","sharp"],"Bus":["bus"],"BusOutline":["bus","outline"],"BusSharp":["bus","sharp"],"Business":["business"],"BusinessOutline":["business","outline"],"BusinessSharp":["business","sharp"],"Cafe":["cafe","coffee","cup"],"CafeOutline":["cafe","coffee","cup","outline"],"CafeSharp":["cafe","coffee","cup","sharp"],"Calculator":["arithmetic","calculator","math"],"CalculatorOutline":["arithmetic","calculator","math","outline"],"CalculatorSharp":["arithmetic","calculator","math","sharp"],"Calendar":["calendar","date","month","week"],"CalendarOutline":["calendar","date","month","outline","week"],"CalendarSharp":["calendar","date","month","sharp","week"],"Call":["call","telephone"],"CallOutline":["call","outline","telephone"],"CallSharp":["call","sharp","telephone"],"Camera":["camera","image","photo"],"CameraOutline":["camera","image","outline","photo"],"CameraReverse":["camera","reverse"],"CameraReverseOutline":["camera","outline","reverse"],"CameraReverseSharp":["camera","reverse","sharp"],"CameraSharp":["camera","image","photo","sharp"],"Car":["car"],"CarOutline":["car","outline"],"CarSharp":["car","sharp"],"CarSport":["car","sport"],"CarSportOutline":["car","outline","sport"],"CarSportSharp":["car","sharp","sport"],"Card":["$","card","cash","credit","debit","dollars","money","price","shopping"],"CardOutline":["$","card","cash","credit","debit","dollars","money","outline","price","shopping"],"CardSharp":["$","card","cash","credit","debit","dollars","money","price","sharp","shopping"],"CaretBack":["back","caret"],"CaretBackCircle":["back","caret","circle"],"CaretBackCircleOutline":["back","caret","circle","outline"],"CaretBackCircleSharp":["back","caret","circle","sharp"],"CaretBackOutline":["back","caret","outline"],"CaretBackSharp":["back","caret","sharp"],"CaretDown":["caret","down"],"CaretDownCircle":["caret","circle","down"],"CaretDownCircleOutline":["caret","circle","down","outline"],"CaretDownCircleSharp":["caret","circle","down","sharp"],"CaretDownOutline":["caret","down","outline"],"CaretDownSharp":["caret","down","sharp"],"CaretForward":["caret","forward"],"CaretForwardCircle":["caret","circle","forward"],"CaretForwardCircleOutline":["caret","circle","forward","outline"],"CaretForwardCircleSharp":["caret","circle","forward","sharp"],"CaretForwardOutline":["caret","forward","outline"],"CaretForwardSharp":["caret","forward","sharp"],"CaretUp":["caret","up"],"CaretUpCircle":["caret","circle","up"],"CaretUpCircleOutline":["caret","circle","outline","up"],"CaretUpCircleSharp":["caret","circle","sharp","up"],"CaretUpOutline":["caret","outline","up"],"CaretUpSharp":["caret","sharp","up"],"Cart":["cart"],"CartOutline":["cart","outline"],"CartSharp":["cart","sharp"],"Cash":["$","cash","credit","debit","dollars","money","price","shopping"],"CashOutline":["$","cash","credit","debit","dollars","money","outline","price","shopping"],"CashSharp":["$","cash","credit","debit","dollars","money","price","sharp","shopping"],"Cellular":["cellular"],"CellularOutline":["cellular","outline"],"CellularSharp":["cellular","sharp"],"Chatbox":["chatbox"],"ChatboxEllipses":["chatbox","ellipses"],"ChatboxEllipsesOutline":["chatbox","ellipses","outline"],"ChatboxEllipsesSharp":["chatbox","ellipses","sharp"],"ChatboxOutline":["chatbox","outline"],"ChatboxSharp":["chatbox","sharp"],"Chatbubble":["chatbubble"],"ChatbubbleEllipses":["chatbubble","ellipses"],"ChatbubbleEllipsesOutline":["chatbubble","ellipses","outline"],"ChatbubbleEllipsesSharp":["chatbubble","ellipses","sharp"],"ChatbubbleOutline":["chatbubble","outline"],"ChatbubbleSharp":["chatbubble","sharp"],"Chatbubbles":["chatbubbles","talk"],"ChatbubblesOutline":["chatbubbles","outline","talk"],"ChatbubblesSharp":["chatbubbles","sharp","talk"],"Checkbox":["checkbox"],"CheckboxOutline":["checkbox","outline"],"CheckboxSharp":["checkbox","sharp"],"Checkmark":["checkmark","circle"],"CheckmarkCircle":["checkmark","circle"],"CheckmarkCircleOutline":["checkmark","circle","outline"],"CheckmarkCircleSharp":["checkmark","circle","sharp"],"CheckmarkDone":["checkmark","done"],"CheckmarkDoneCircle":["checkmark","circle","done"],"CheckmarkDoneCircleOutline":["checkmark","circle","done","outline"],"CheckmarkDoneCircleSharp":["checkmark","circle","done","sharp"],"CheckmarkDoneOutline":["checkmark","done","outline"],"CheckmarkDoneSharp":["checkmark","done","sharp"],"CheckmarkOutline":["checkmark","outline"],"CheckmarkSharp":["checkmark","circle","sharp"],"ChevronBack":["back","chevron"],"ChevronBackCircle":["back","chevron","circle"],"ChevronBackCircleOutline":["back","chevron","circle","outline"],"ChevronBackCircleSharp":["back","chevron","circle","sharp"],"ChevronBackOutline":["back","chevron","outline"],"ChevronBackSharp":["back","chevron","sharp"],"ChevronDown":["chevron","down"],"ChevronDownCircle":["chevron","circle","down"],"ChevronDownCircleOutline":["chevron","circle","down","outline"],"ChevronDownCircleSharp":["chevron","circle","down","sharp"],"ChevronDownOutline":["chevron","down","outline"],"ChevronDownSharp":["chevron","down","sharp"],"ChevronForward":["chevron","forward"],"ChevronForwardCircle":["chevron","circle","forward"],"ChevronForwardCircleOutline":["chevron","circle","forward","outline"],"ChevronForwardCircleSharp":["chevron","circle","forward","sharp"],"ChevronForwardOutline":["chevron","forward","outline"],"ChevronForwardSharp":["chevron","forward","sharp"],"ChevronUp":["chevron","up"],"ChevronUpCircle":["chevron","circle","up"],"ChevronUpCircleOutline":["chevron","circle","outline","up"],"ChevronUpCircleSharp":["chevron","circle","sharp","up"],"ChevronUpOutline":["chevron","outline","up"],"ChevronUpSharp":["chevron","sharp","up"],"Clipboard":["clipboard","write"],"ClipboardOutline":["clipboard","outline","write"],"ClipboardSharp":["clipboard","sharp","write"],"Close":["circle","close","delete","remove"],"CloseCircle":["circle","close","delete","remove"],"CloseCircleOutline":["circle","close","delete","outline","remove"],"CloseCircleSharp":["circle","close","delete","remove","sharp"],"CloseOutline":["circle","close","delete","outline","remove"],"CloseSharp":["circle","close","delete","remove","sharp"],"Cloud":["circle","cloud","storage","weather","whether"],"CloudCircle":["circle","cloud","storage","weather","whether"],"CloudCircleOutline":["circle","cloud","outline","storage","weather","whether"],"CloudCircleSharp":["circle","cloud","sharp","storage","weather","whether"],"CloudDone":["cloud","done"],"CloudDoneOutline":["cloud","done","outline"],"CloudDoneSharp":["cloud","done","sharp"],"CloudDownload":["cloud","download","storage"],"CloudDownloadOutline":["cloud","download","outline","storage"],"CloudDownloadSharp":["cloud","download","sharp","storage"],"CloudOffline":["cloud","offline"],"CloudOfflineOutline":["cloud","offline","outline"],"CloudOfflineSharp":["cloud","offline","sharp"],"CloudOutline":["circle","cloud","outline","storage","weather","whether"],"CloudSharp":["circle","cloud","sharp","storage","weather","whether"],"CloudUpload":["cloud","storage","upload"],"CloudUploadOutline":["cloud","outline","storage","upload"],"CloudUploadSharp":["cloud","sharp","storage","upload"],"Cloudy":["cloudy","overcast","weather","whether"],"CloudyNight":["cloudy","night","overcast","weather","whether"],"CloudyNightOutline":["cloudy","night","outline","overcast","weather","whether"],"CloudyNightSharp":["cloudy","night","overcast","sharp","weather","whether"],"CloudyOutline":["cloudy","outline","overcast","weather","whether"],"CloudySharp":["cloudy","overcast","sharp","weather","whether"],"Code":["code","develop","hacker","program"],"CodeDownload":["code","develop","download","hacker","program"],"CodeDownloadOutline":["code","develop","download","hacker","outline","program"],"CodeDownloadSharp":["code","develop","download","hacker","program","sharp"],"CodeOutline":["code","develop","hacker","outline","program"],"CodeSharp":["code","develop","hacker","program","sharp"],"CodeSlash":["code","slash"],"CodeSlashOutline":["code","outline","slash"],"CodeSlashSharp":["code","sharp","slash"],"CodeWorking":["code","develop","hacker","program","working"],"CodeWorkingOutline":["code","develop","hacker","outline","program","working"],"CodeWorkingSharp":["code","develop","hacker","program","sharp","working"],"Cog":["cog","gear","options","settings"],"CogOutline":["cog","gear","options","outline","settings"],"CogSharp":["cog","gear","options","settings","sharp"],"ColorFill":["color","fill"],"ColorFillOutline":["color","fill","outline"],"ColorFillSharp":["color","fill","sharp"],"ColorFilter":["color","filter"],"ColorFilterOutline":["color","filter","outline"],"ColorFilterSharp":["color","filter","sharp"],"ColorPalette":["color","palette"],"ColorPaletteOutline":["color","outline","palette"],"ColorPaletteSharp":["color","palette","sharp"],"ColorWand":["color","wand"],"ColorWandOutline":["color","outline","wand"],"ColorWandSharp":["color","sharp","wand"],"Compass":["compass","directions","location","navigation"],"CompassOutline":["compass","directions","location","navigation","outline"],"CompassSharp":["compass","directions","location","navigation","sharp"],"Construct":["construct"],"ConstructOutline":["construct","outline"],"ConstructSharp":["construct","sharp"],"Contract":["contract"],"ContractOutline":["contract","outline"],"ContractSharp":["contract","sharp"],"Contrast":["contrast","dark","images","levels","light","settings"],"ContrastOutline":["contrast","dark","images","levels","light","outline","settings"],"ContrastSharp":["contrast","dark","images","levels","light","settings","sharp"],"Copy":["copy","duplicate","paper"],"CopyOutline":["copy","duplicate","outline","paper"],"CopySharp":["copy","duplicate","paper","sharp"],"Create":["create","edit"],"CreateOutline":["create","edit","outline"],"CreateSharp":["create","edit","sharp"],"Crop":["crop"],"CropOutline":["crop","outline"],"CropSharp":["crop","sharp"],"Cube":["box","container","cube","square"],"CubeOutline":["box","container","cube","outline","square"],"CubeSharp":["box","container","cube","sharp","square"],"Cut":["cut"],"CutOutline":["cut","outline"],"CutSharp":["cut","sharp"],"Desktop":["desktop"],"DesktopOutline":["desktop","outline"],"DesktopSharp":["desktop","sharp"],"Disc":["cd","disc","vinyl"],"DiscOutline":["cd","disc","outline","vinyl"],"DiscSharp":["cd","disc","sharp","vinyl"],"Document":["document","file","paper"],"DocumentAttach":["attach","document"],"DocumentAttachOutline":["attach","document","outline"],"DocumentAttachSharp":["attach","document","sharp"],"DocumentOutline":["document","file","outline","paper"],"DocumentSharp":["document","file","paper","sharp"],"DocumentText":["document","text"],"DocumentTextOutline":["document","outline","text"],"DocumentTextSharp":["document","sharp","text"],"Documents":["documents"],"DocumentsOutline":["documents","outline"],"DocumentsSharp":["documents","sharp"],"Download":["download","export"],"DownloadOutline":["download","export","outline"],"DownloadSharp":["download","export","sharp"],"Duplicate":["duplicate"],"DuplicateOutline":["duplicate","outline"],"DuplicateSharp":["duplicate","sharp"],"Ear":["ear"],"EarOutline":["ear","outline"],"EarSharp":["ear","sharp"],"Earth":["earth"],"EarthOutline":["earth","outline"],"EarthSharp":["earth","sharp"],"Easel":["easel"],"EaselOutline":["easel","outline"],"EaselSharp":["easel","sharp"],"Egg":["baby","bird","birth","egg","twitter"],"EggOutline":["baby","bird","birth","egg","outline","twitter"],"EggSharp":["baby","bird","birth","egg","sharp","twitter"],"Ellipse":["ellipse"],"EllipseOutline":["ellipse","outline"],"EllipseSharp":["ellipse","sharp"],"EllipsisHorizontal":["ellipsis","horizontal"],"EllipsisHorizontalCircle":["circle","ellipsis","horizontal"],"EllipsisHorizontalCircleOutline":["circle","ellipsis","horizontal","outline"],"EllipsisHorizontalCircleSharp":["circle","ellipsis","horizontal","sharp"],"EllipsisHorizontalOutline":["ellipsis","horizontal","outline"],"EllipsisHorizontalSharp":["ellipsis","horizontal","sharp"],"EllipsisVertical":["ellipsis","vertical"],"EllipsisVerticalCircle":["circle","ellipsis","vertical"],"EllipsisVerticalCircleOutline":["circle","ellipsis","outline","vertical"],"EllipsisVerticalCircleSharp":["circle","ellipsis","sharp","vertical"],"EllipsisVerticalOutline":["ellipsis","outline","vertical"],"EllipsisVerticalSharp":["ellipsis","sharp","vertical"],"Enter":["enter"],"EnterOutline":["enter","outline"],"EnterSharp":["enter","sharp"],"Exit":["exit"],"ExitOutline":["exit","outline"],"ExitSharp":["exit","sharp"],"Expand":["expand","resize"],"ExpandOutline":["expand","outline"],"ExpandSharp":["expand","resize","sharp"],"Eye":["exposed","eye","look","see","view"],"EyeOff":["eye","off"],"EyeOffOutline":["eye","off","outline"],"EyeOffSharp":["eye","off","sharp"],"EyeOutline":["exposed","eye","look","outline","see","view"],"EyeSharp":["exposed","eye","look","see","sharp","view"],"Eyedrop":["eyedrop"],"EyedropOutline":["eyedrop","outline"],"EyedropSharp":["eyedrop","sharp"],"FastFood":["fast","food"],"FastFoodOutline":["fast","food","outline"],"FastFoodSharp":["fast","food","sharp"],"Female":["female","girl","lady","woman"],"FemaleOutline":["female","girl","lady","outline","woman"],"FemaleSharp":["female","girl","lady","sharp","woman"],"FileTray":["file","tray"],"FileTrayFull":["file","full","tray"],"FileTrayFullOutline":["file","full","outline","tray"],"FileTrayFullSharp":["file","full","sharp","tray"],"FileTrayOutline":["file","outline","tray"],"FileTraySharp":["file","sharp","tray"],"FileTrayStacked":["file","stacked","tray"],"FileTrayStackedOutline":["file","outline","stacked","tray"],"FileTrayStackedSharp":["file","sharp","stacked","tray"],"Film":["film"],"FilmOutline":["film","outline"],"FilmSharp":["film","sharp"],"Filter":["filter"],"FilterOutline":["filter","outline"],"FilterSharp":["filter","sharp"],"FingerPrint":["finger","print"],"FingerPrintOutline":["finger","outline","print"],"FingerPrintSharp":["finger","print","sharp"],"Fitness":["fitness"],"FitnessOutline":["fitness","outline"],"FitnessSharp":["fitness","sharp"],"Flag":["favorite","flag","marker"],"FlagOutline":["favorite","flag","marker","outline"],"FlagSharp":["favorite","flag","marker","sharp"],"Flame":["fire","flame","heat","hot"],"FlameOutline":["fire","flame","heat","hot","outline"],"FlameSharp":["fire","flame","heat","hot","sharp"],"Flash":["flash","lightning","weather","whether"],"FlashOff":["flash","off"],"FlashOffOutline":["flash","off","outline"],"FlashOffSharp":["flash","off","sharp"],"FlashOutline":["flash","lightning","outline","weather","whether"],"FlashSharp":["flash","lightning","sharp","weather","whether"],"Flashlight":["flashlight"],"FlashlightOutline":["flashlight","outline"],"FlashlightSharp":["flashlight","sharp"],"Flask":["bubbles","flask","mixture","potion"],"FlaskOutline":["bubbles","flask","mixture","outline","potion"],"FlaskSharp":["bubbles","flask","mixture","potion","sharp"],"Flower":["flower"],"FlowerOutline":["flower","outline"],"FlowerSharp":["flower","sharp"],"Folder":["file","folder"],"FolderOpen":["folder","open"],"FolderOpenOutline":["folder","open","outline"],"FolderOpenSharp":["folder","open","sharp"],"FolderOutline":["file","folder","outline"],"FolderSharp":["file","folder","sharp"],"Football":["football","soccer"],"FootballOutline":["football","outline","soccer"],"FootballSharp":["football","sharp","soccer"],"Funnel":["funnel","sort"],"FunnelOutline":["funnel","outline","sort"],"FunnelSharp":["funnel","sharp","sort"],"GameController":["controller","game"],"GameControllerOutline":["controller","game","outline"],"GameControllerSharp":["controller","game","sharp"],"Gift":["gift"],"GiftOutline":["gift","outline"],"GiftSharp":["gift","sharp"],"GitBranch":["branch","git"],"GitBranchOutline":["branch","git","outline"],"GitBranchSharp":["branch","git","sharp"],"GitCommit":["commit","git"],"GitCommitOutline":["commit","git","outline"],"GitCommitSharp":["commit","git","sharp"],"GitCompare":["compare","git"],"GitCompareOutline":["compare","git","outline"],"GitCompareSharp":["compare","git","sharp"],"GitMerge":["git","merge"],"GitMergeOutline":["git","merge","outline"],"GitMergeSharp":["git","merge","sharp"],"GitNetwork":["git","network"],"GitNetworkOutline":["git","network","outline"],"GitNetworkSharp":["git","network","sharp"],"GitPullRequest":["git","pull","request"],"GitPullRequestOutline":["git","outline","pull","request"],"GitPullRequestSharp":["git","pull","request","sharp"],"Glasses":["glasses","look","reading","see","steve"],"GlassesOutline":["glasses","look","outline","reading","see","steve"],"GlassesSharp":["glasses","look","reading","see","sharp","steve"],"Globe":["globe","internet","world"],"GlobeOutline":["globe","internet","outline","world"],"GlobeSharp":["globe","internet","sharp","world"],"Golf":["golf"],"GolfOutline":["golf","outline"],"GolfSharp":["golf","sharp"],"Grid":["grid","menu"],"GridOutline":["grid","menu","outline"],"GridSharp":["grid","menu","sharp"],"Hammer":["hammer","options","settings","tools"],"HammerOutline":["hammer","options","outline","settings","tools"],"HammerSharp":["hammer","options","settings","sharp","tools"],"HandLeft":["hand","left"],"HandLeftOutline":["hand","left","outline"],"HandLeftSharp":["hand","left","sharp"],"HandRight":["hand","right"],"HandRightOutline":["hand","outline","right"],"HandRightSharp":["hand","right","sharp"],"Happy":["fun","good","happy","like","smile","yes"],"HappyOutline":["fun","good","happy","like","outline","smile","yes"],"HappySharp":["fun","good","happy","like","sharp","smile","yes"],"HardwareChip":["chip","hardware"],"HardwareChipOutline":["chip","hardware","outline"],"HardwareChipSharp":["chip","hardware","sharp"],"Headset":["headset"],"HeadsetOutline":["headset","outline"],"HeadsetSharp":["headset","sharp"],"Heart":["heart","love"],"HeartCircle":["circle","heart","love"],"HeartCircleOutline":["circle","heart","love","outline"],"HeartCircleSharp":["circle","heart","love","sharp"],"HeartDislike":["dislike","heart","love"],"HeartDislikeCircle":["circle","dislike","heart","love"],"HeartDislikeCircleOutline":["circle","dislike","heart","love","outline"],"HeartDislikeCircleSharp":["circle","dislike","heart","love","sharp"],"HeartDislikeOutline":["dislike","heart","love","outline"],"HeartDislikeSharp":["dislike","heart","love","sharp"],"HeartHalf":["half","heart","love"],"HeartHalfOutline":["half","heart","outline"],"HeartHalfSharp":["half","heart","love","sharp"],"HeartOutline":["heart","love","outline"],"HeartSharp":["heart","love","sharp"],"Help":["?","circle","help","information","question"],"HelpBuoy":["?","buoy","help","question"],"HelpBuoyOutline":["?","buoy","help","outline","question"],"HelpBuoySharp":["?","buoy","help","question","sharp"],"HelpCircle":["?","circle","help","information","question"],"HelpCircleOutline":["?","circle","help","information","outline","question"],"HelpCircleSharp":["?","circle","help","information","question","sharp"],"HelpOutline":["help","outline"],"HelpSharp":["?","circle","help","information","question","sharp"],"Home":["home","house"],"HomeOutline":["home","house","outline"],"HomeSharp":["home","house","sharp"],"Hourglass":["hourglass","time"],"HourglassOutline":["hourglass","outline","time"],"HourglassSharp":["hourglass","sharp","time"],"IceCream":["cream","ice"],"IceCreamOutline":["cream","ice","outline"],"IceCreamSharp":["cream","ice","sharp"],"Image":["camera","image","photo"],"ImageOutline":["camera","image","outline","photo"],"ImageSharp":["camera","image","photo","sharp"],"Images":["images","photo"],"ImagesOutline":["images","outline","photo"],"ImagesSharp":["images","photo","sharp"],"Infinite":["forever","infinite","loop"],"InfiniteOutline":["forever","infinite","loop","outline"],"InfiniteSharp":["forever","infinite","loop","sharp"],"Information":["circle","help","information","knowledge"],"InformationCircle":["circle","help","information","knowledge"],"InformationCircleOutline":["circle","help","information","knowledge","outline"],"InformationCircleSharp":["circle","help","information","knowledge","sharp"],"InformationOutline":["information","outline"],"InformationSharp":["circle","help","information","knowledge","sharp"],"Journal":["journal"],"JournalOutline":["journal","outline"],"JournalSharp":["journal","sharp"],"Key":["access","key"],"KeyOutline":["access","key","outline"],"KeySharp":["access","key","sharp"],"Keypad":["keypad","type"],"KeypadOutline":["keypad","outline","type"],"KeypadSharp":["keypad","sharp","type"],"Language":["language"],"LanguageOutline":["language","outline"],"LanguageSharp":["language","sharp"],"Laptop":["apple","laptop","macbook","osx"],"LaptopOutline":["apple","laptop","macbook","osx","outline"],"LaptopSharp":["apple","laptop","macbook","osx","sharp"],"Layers":["layers"],"LayersOutline":["layers","outline"],"LayersSharp":["layers","sharp"],"Leaf":["green","leaf","nature","plant","recycle"],"LeafOutline":["green","leaf","nature","outline","plant","recycle"],"LeafSharp":["green","leaf","nature","plant","recycle","sharp"],"Library":["library"],"LibraryOutline":["library","outline"],"LibrarySharp":["library","sharp"],"Link":["anchor","attach","chain","href","link"],"LinkOutline":["anchor","attach","chain","href","link","outline"],"LinkSharp":["anchor","attach","chain","href","link","sharp"],"List":["list"],"ListCircle":["circle","list"],"ListCircleOutline":["circle","list","outline"],"ListCircleSharp":["circle","list","sharp"],"ListOutline":["list","outline"],"ListSharp":["list","sharp"],"Locate":["gps","locate","maps","navigate"],"LocateOutline":["gps","locate","maps","navigate","outline"],"LocateSharp":["gps","locate","maps","navigate","sharp"],"Location":["location"],"LocationOutline":["location","outline"],"LocationSharp":["location","sharp"],"LockClosed":["closed","lock"],"LockClosedOutline":["closed","lock","outline"],"LockClosedSharp":["closed","lock","sharp"],"LockOpen":["lock","open"],"LockOpenOutline":["lock","open","outline"],"LockOpenSharp":["lock","open","sharp"],"LogIn":["in","log","signin"],"LogInOutline":["in","log","outline","signin"],"LogInSharp":["in","log","sharp","signin"],"LogOut":["log","out","signout"],"LogOutOutline":["log","out","outline","signout"],"LogOutSharp":["log","out","sharp","signout"],"LogoAmazon":["amazon","logo"],"LogoAmplify":["amplify","logo"],"LogoAndroid":["android","logo"],"LogoAngular":["angular","logo"],"LogoApple":["apple","logo"],"LogoAppleAppstore":["apple","appstore","logo"],"LogoBitbucket":["bitbucket","logo"],"LogoBitcoin":["bitcoin","logo"],"LogoBuffer":["buffer","logo"],"LogoCapacitor":["capacitor","logo"],"LogoChrome":["chrome","logo"],"LogoClosedCaptioning":["captioning","closed","logo"],"LogoCodepen":["codepen","logo"],"LogoCss3":["css3","logo"],"LogoDesignernews":["designernews","logo"],"LogoDribbble":["dribbble","logo"],"LogoDropbox":["dropbox","logo"],"LogoEdge":["edge","logo"],"LogoElectron":["electron","logo"],"LogoEuro":["euro","logo"],"LogoFacebook":["facebook","logo"],"LogoFirebase":["firebase","logo"],"LogoFirefox":["firefox","logo"],"LogoFlickr":["flickr","logo"],"LogoFoursquare":["foursquare","logo"],"LogoGithub":["github","logo"],"LogoGoogle":["google","logo"],"LogoGooglePlaystore":["google","logo","playstore"],"LogoHackernews":["hackernews","logo"],"LogoHtml5":["html5","logo"],"LogoInstagram":["instagram","logo"],"LogoIonic":["ionic","logo"],"LogoIonitron":["ionitron","logo"],"LogoJavascript":["javascript","logo"],"LogoLaravel":["laravel","logo"],"LogoLinkedin":["linkedin","logo"],"LogoMarkdown":["logo","markdown"],"LogoNoSmoking":["logo","no","smoking"],"LogoNodejs":["logo","nodejs"],"LogoNpm":["logo","npm"],"LogoOctocat":["logo","octocat"],"LogoPinterest":["logo","pinterest"],"LogoPlaystation":["logo","playstation"],"LogoPwa":["logo","pwa"],"LogoPython":["logo","python"],"LogoReact":["logo","react"],"LogoReddit":["logo","reddit"],"LogoRss":["logo","rss"],"LogoSass":["logo","sass"],"LogoSkype":["logo","skype"],"LogoSlack":["logo","slack"],"LogoSnapchat":["logo","snapchat"],"LogoStackoverflow":["logo","stackoverflow"],"LogoSteam":["logo","steam"],"LogoStencil":["logo","stencil"],"LogoTumblr":["logo","tumblr"],"LogoTux":["logo","tux"],"LogoTwitch":["logo","twitch"],"LogoTwitter":["logo","twitter"],"LogoUsd":["logo","usd"],"LogoVimeo":["logo","vimeo"],"LogoVk":["logo","vk"],"LogoVue":["logo","vue"],"LogoWebComponent":["component","logo","web"],"LogoWhatsapp":["logo","whatsapp"],"LogoWindows":["logo","windows"],"LogoWordpress":["logo","wordpress"],"LogoXbox":["logo","xbox"],"LogoXing":["logo","xing"],"LogoYahoo":["logo","yahoo"],"LogoYen":["logo","yen"],"LogoYoutube":["logo","youtube"],"Magnet":["attraction","magnet","sticky"],"MagnetOutline":["attraction","magnet","outline","sticky"],"MagnetSharp":["attraction","magnet","sharp","sticky"],"Mail":["email","mail"],"MailOpen":["mail","open"],"MailOpenOutline":["mail","open","outline"],"MailOpenSharp":["mail","open","sharp"],"MailOutline":["email","mail","outline"],"MailSharp":["email","mail","sharp"],"MailUnread":["mail","unread"],"MailUnreadOutline":["mail","outline","unread"],"MailUnreadSharp":["mail","sharp","unread"],"Male":["boy","dude","guy","male"],"MaleFemale":["female","male"],"MaleFemaleOutline":["female","male","outline"],"MaleFemaleSharp":["female","male","sharp"],"MaleOutline":["male","outline"],"MaleSharp":["boy","dude","guy","male","sharp"],"Man":["boy","dude","guy","male","man"],"ManOutline":["boy","dude","guy","male","man","outline"],"ManSharp":["boy","dude","guy","male","man","sharp"],"Map":["gps","map","navigation","pin"],"MapOutline":["gps","map","navigation","outline","pin"],"MapSharp":["gps","map","navigation","pin","sharp"],"Medal":["medal"],"MedalOutline":["medal","outline"],"MedalSharp":["medal","sharp"],"Medical":["medical"],"MedicalOutline":["medical","outline"],"MedicalSharp":["medical","sharp"],"Medkit":["case","disease","firstaid","health","medkit","sick"],"MedkitOutline":["case","disease","firstaid","health","medkit","outline","sick"],"MedkitSharp":["case","disease","firstaid","health","medkit","sharp","sick"],"Megaphone":["megaphone"],"MegaphoneOutline":["megaphone","outline"],"MegaphoneSharp":["megaphone","sharp"],"Menu":["menu"],"MenuOutline":["menu","outline"],"MenuSharp":["menu","sharp"],"Mic":["mic","noise","sound","speaker","talk"],"MicCircle":["circle","mic","noise","sound","speaker","talk"],"MicCircleOutline":["circle","mic","noise","outline","sound","speaker","talk"],"MicCircleSharp":["circle","mic","noise","sharp","sound","speaker","talk"],"MicOff":["mic","noise","off","sound","speaker","talk"],"MicOffCircle":["circle","mic","noise","off","sound","speaker","talk"],"MicOffCircleOutline":["circle","mic","noise","off","outline","sound","speaker","talk"],"MicOffCircleSharp":["circle","mic","noise","off","sharp","sound","speaker","talk"],"MicOffOutline":["mic","noise","off","outline","sound","speaker","talk"],"MicOffSharp":["mic","noise","off","sharp","sound","speaker","talk"],"MicOutline":["mic","noise","outline","sound","speaker","talk"],"MicSharp":["mic","noise","sharp","sound","speaker","talk"],"Moon":["dark","moon","night","sky"],"MoonOutline":["dark","moon","night","outline","sky"],"MoonSharp":["dark","moon","night","sharp","sky"],"Move":["move"],"MoveOutline":["move","outline"],"MoveSharp":["move","sharp"],"MusicalNote":["listening","musical","noise","note","play","sound"],"MusicalNoteOutline":["listening","musical","noise","note","outline","play","sound"],"MusicalNoteSharp":["listening","musical","noise","note","play","sharp","sound"],"MusicalNotes":["listening","musical","noise","notes","play","sound"],"MusicalNotesOutline":["listening","musical","noise","notes","outline","play","sound"],"MusicalNotesSharp":["listening","musical","noise","notes","play","sharp","sound"],"Navigate":["gps","location","map","navigate","pin"],"NavigateCircle":["circle","gps","location","map","navigate","pin"],"NavigateCircleOutline":["circle","gps","location","map","navigate","outline","pin"],"NavigateCircleSharp":["circle","gps","location","map","navigate","pin","sharp"],"NavigateOutline":["gps","location","map","navigate","outline","pin"],"NavigateSharp":["gps","location","map","navigate","pin","sharp"],"Newspaper":["newspaper"],"NewspaperOutline":["newspaper","outline"],"NewspaperSharp":["newspaper","sharp"],"Notifications":["notifications"],"NotificationsCircle":["circle","notifications"],"NotificationsCircleOutline":["circle","notifications","outline"],"NotificationsCircleSharp":["circle","notifications","sharp"],"NotificationsOff":["notifications","off"],"NotificationsOffCircle":["circle","notifications","off"],"NotificationsOffCircleOutline":["circle","notifications","off","outline"],"NotificationsOffCircleSharp":["circle","notifications","off","sharp"],"NotificationsOffOutline":["notifications","off","outline"],"NotificationsOffSharp":["notifications","off","sharp"],"NotificationsOutline":["notifications","outline"],"NotificationsSharp":["notifications","sharp"],"Nuclear":["danger","hazard","nuclear","warning"],"NuclearOutline":["danger","hazard","nuclear","outline","warning"],"NuclearSharp":["danger","hazard","nuclear","sharp","warning"],"Nutrition":["nutrition"],"NutritionOutline":["nutrition","outline"],"NutritionSharp":["nutrition","sharp"],"Open":["open"],"OpenOutline":["open","outline"],"OpenSharp":["open","sharp"],"Options":["options"],"OptionsOutline":["options","outline"],"OptionsSharp":["options","sharp"],"PaperPlane":["paper","plane"],"PaperPlaneOutline":["outline","paper","plane"],"PaperPlaneSharp":["paper","plane","sharp"],"PartlySunny":["partly","sunny"],"PartlySunnyOutline":["outline","partly","sunny"],"PartlySunnySharp":["partly","sharp","sunny"],"Pause":["break","freeze","hold","music","pause"],"PauseCircle":["break","circle","freeze","hold","music","pause"],"PauseCircleOutline":["break","circle","freeze","hold","music","outline","pause"],"PauseCircleSharp":["break","circle","freeze","hold","music","pause","sharp"],"PauseOutline":["break","freeze","hold","music","outline","pause"],"PauseSharp":["break","freeze","hold","music","pause","sharp"],"Paw":["paw"],"PawOutline":["outline","paw"],"PawSharp":["paw","sharp"],"Pencil":["pencil"],"PencilOutline":["outline","pencil"],"PencilSharp":["pencil","sharp"],"People":["head","human","people","person","stalker","users"],"PeopleCircle":["circle","head","human","people","person","stalker","users"],"PeopleCircleOutline":["circle","head","human","outline","people","person","stalker","users"],"PeopleCircleSharp":["circle","head","human","people","person","sharp","stalker","users"],"PeopleOutline":["head","human","outline","people","person","stalker","users"],"PeopleSharp":["head","human","people","person","sharp","stalker","users"],"Person":["head","human","person","staff","users"],"PersonAdd":["add","head","human","member","new","person","staff","users"],"PersonAddOutline":["add","head","human","member","new","outline","person","staff","users"],"PersonAddSharp":["add","head","human","member","new","person","sharp","staff","users"],"PersonCircle":["circle","head","human","person","staff","users"],"PersonCircleOutline":["circle","head","human","outline","person","staff","users"],"PersonCircleSharp":["circle","head","human","person","sharp","staff","users"],"PersonOutline":["head","human","outline","person","staff","users"],"PersonRemove":["person","remove"],"PersonRemoveOutline":["outline","person","remove"],"PersonRemoveSharp":["person","remove","sharp"],"PersonSharp":["head","human","person","sharp","staff","users"],"PhoneLandscape":["landscape","phone"],"PhoneLandscapeOutline":["landscape","outline","phone"],"PhoneLandscapeSharp":["landscape","phone","sharp"],"PhonePortrait":["phone","portrait"],"PhonePortraitOutline":["outline","phone","portrait"],"PhonePortraitSharp":["phone","portrait","sharp"],"PieChart":["chart","pie"],"PieChartOutline":["chart","outline","pie"],"PieChartSharp":["chart","pie","sharp"],"Pin":["gps","location","navigation","pin"],"PinOutline":["gps","location","navigation","outline","pin"],"PinSharp":["gps","location","navigation","pin","sharp"],"Pint":["pint"],"PintOutline":["outline","pint"],"PintSharp":["pint","sharp"],"Pizza":["drink","eat","food","pizza"],"PizzaOutline":["drink","eat","food","outline","pizza"],"PizzaSharp":["drink","eat","food","pizza","sharp"],"Planet":["globe","home","nature","planet","space","world"],"PlanetOutline":["globe","home","nature","outline","planet","space","world"],"PlanetSharp":["globe","home","nature","planet","sharp","space","world"],"Play":["arrow","music","play","right","watch"],"PlayBack":["back","play"],"PlayBackCircle":["back","circle","play"],"PlayBackCircleOutline":["back","circle","outline","play"],"PlayBackCircleSharp":["back","circle","play","sharp"],"PlayBackOutline":["back","outline","play"],"PlayBackSharp":["back","play","sharp"],"PlayCircle":["arrow","circle","music","play","right","watch"],"PlayCircleOutline":["arrow","circle","music","outline","play","right","watch"],"PlayCircleSharp":["arrow","circle","music","play","right","sharp","watch"],"PlayForward":["forward","play"],"PlayForwardCircle":["circle","forward","play"],"PlayForwardCircleOutline":["circle","forward","outline","play"],"PlayForwardCircleSharp":["circle","forward","play","sharp"],"PlayForwardOutline":["forward","outline","play"],"PlayForwardSharp":["forward","play","sharp"],"PlayOutline":["arrow","music","outline","play","right","watch"],"PlaySharp":["arrow","music","play","right","sharp","watch"],"PlaySkipBack":["back","play","skip"],"PlaySkipBackCircle":["back","circle","play","skip"],"PlaySkipBackCircleOutline":["back","circle","outline","play","skip"],"PlaySkipBackCircleSharp":["back","circle","play","sharp","skip"],"PlaySkipBackOutline":["back","outline","play","skip"],"PlaySkipBackSharp":["back","play","sharp","skip"],"PlaySkipForward":["forward","play","skip"],"PlaySkipForwardCircle":["circle","forward","play","skip"],"PlaySkipForwardCircleOutline":["circle","forward","outline","play","skip"],"PlaySkipForwardCircleSharp":["circle","forward","play","sharp","skip"],"PlaySkipForwardOutline":["forward","outline","play","skip"],"PlaySkipForwardSharp":["forward","play","sharp","skip"],"Podium":["award","compete","competition","lose","podium","win"],"PodiumOutline":["award","compete","competition","lose","outline","podium","win"],"PodiumSharp":["award","compete","competition","lose","podium","sharp","win"],"Power":["off","on","power"],"PowerOutline":["off","on","outline","power"],"PowerSharp":["off","on","power","sharp"],"Pricetag":["$","commerce","items","money","pricetag","shopping"],"PricetagOutline":["$","commerce","items","money","outline","pricetag","shopping"],"PricetagSharp":["$","commerce","items","money","pricetag","sharp","shopping"],"Pricetags":["$","commerce","items","money","pricetags","shopping"],"PricetagsOutline":["$","commerce","items","money","outline","pricetags","shopping"],"PricetagsSharp":["$","commerce","items","money","pricetags","sharp","shopping"],"Print":["print"],"PrintOutline":["outline","print"],"PrintSharp":["print","sharp"],"Pulse":["hot","live","pulse","rate"],"PulseOutline":["hot","live","outline","pulse","rate"],"PulseSharp":["hot","live","pulse","rate","sharp"],"Push":["push"],"PushOutline":["outline","push"],"PushSharp":["push","sharp"],"QrCode":["code","qr"],"QrCodeOutline":["code","outline","qr"],"QrCodeSharp":["code","qr","sharp"],"Radio":["music","radio"],"RadioButtonOff":["button","off","radio"],"RadioButtonOffOutline":["button","off","outline","radio"],"RadioButtonOffSharp":["button","off","radio","sharp"],"RadioButtonOn":["button","on","radio"],"RadioButtonOnOutline":["button","on","outline","radio"],"RadioButtonOnSharp":["button","on","radio","sharp"],"RadioOutline":["music","outline","radio"],"RadioSharp":["music","radio","sharp"],"Rainy":["cloud","rainy","water","weather","whether"],"RainyOutline":["cloud","outline","rainy","water","weather","whether"],"RainySharp":["cloud","rainy","sharp","water","weather","whether"],"Reader":["reader"],"ReaderOutline":["outline","reader"],"ReaderSharp":["reader","sharp"],"Receipt":["receipt"],"ReceiptOutline":["outline","receipt"],"ReceiptSharp":["receipt","sharp"],"Recording":["film","recording","tape","voicemail"],"RecordingOutline":["film","outline","recording","tape","voicemail"],"RecordingSharp":["film","recording","sharp","tape","voicemail"],"Refresh":["circle","refresh","reload","renew","reset"],"RefreshCircle":["circle","refresh","reload","renew","reset"],"RefreshCircleOutline":["circle","outline","refresh","reload","renew","reset"],"RefreshCircleSharp":["circle","refresh","reload","renew","reset","sharp"],"RefreshOutline":["outline","refresh"],"RefreshSharp":["circle","refresh","reload","renew","reset","sharp"],"Reload":["reload"],"ReloadCircle":["circle","reload"],"ReloadCircleOutline":["circle","outline","reload"],"ReloadCircleSharp":["circle","reload","sharp"],"ReloadOutline":["outline","reload"],"ReloadSharp":["reload","sharp"],"Remove":["circle","minus","remove","subtract"],"RemoveCircle":["circle","minus","remove","subtract"],"RemoveCircleOutline":["circle","minus","outline","remove","subtract"],"RemoveCircleSharp":["circle","minus","remove","sharp","subtract"],"RemoveOutline":["outline","remove"],"RemoveSharp":["circle","minus","remove","sharp","subtract"],"ReorderFour":["four","reorder"],"ReorderFourOutline":["four","outline","reorder"],"ReorderFourSharp":["four","reorder","sharp"],"ReorderThree":["reorder","three"],"ReorderThreeOutline":["outline","reorder","three"],"ReorderThreeSharp":["reorder","sharp","three"],"ReorderTwo":["reorder","two"],"ReorderTwoOutline":["outline","reorder","two"],"ReorderTwoSharp":["reorder","sharp","two"],"Repeat":["repeat"],"RepeatOutline":["outline","repeat"],"RepeatSharp":["repeat","sharp"],"Resize":["resize"],"ResizeOutline":["outline","resize"],"ResizeSharp":["resize","sharp"],"Restaurant":["eat","restaurant"],"RestaurantOutline":["eat","outline","restaurant"],"RestaurantSharp":["eat","restaurant","sharp"],"ReturnDownBack":["back","down","return"],"ReturnDownBackOutline":["back","down","outline","return"],"ReturnDownBackSharp":["back","down","return","sharp"],"ReturnDownForward":["down","forward","return"],"ReturnDownForwardOutline":["down","forward","outline","return"],"ReturnDownForwardSharp":["down","forward","return","sharp"],"ReturnUpBack":["back","return","up"],"ReturnUpBackOutline":["back","outline","return","up"],"ReturnUpBackSharp":["back","return","sharp","up"],"ReturnUpForward":["forward","return","up"],"ReturnUpForwardOutline":["forward","outline","return","up"],"ReturnUpForwardSharp":["forward","return","sharp","up"],"Ribbon":["ribbon"],"RibbonOutline":["outline","ribbon"],"RibbonSharp":["ribbon","sharp"],"Rocket":["rocket"],"RocketOutline":["outline","rocket"],"RocketSharp":["rocket","sharp"],"Rose":["flower","rose"],"RoseOutline":["flower","outline","rose"],"RoseSharp":["flower","rose","sharp"],"Sad":["bad","cry","no","sad"],"SadOutline":["bad","cry","no","outline","sad"],"SadSharp":["bad","cry","no","sad","sharp"],"Save":["save"],"SaveOutline":["outline","save"],"SaveSharp":["save","sharp"],"Scan":["scan"],"ScanCircle":["circle","scan"],"ScanCircleOutline":["circle","outline","scan"],"ScanCircleSharp":["circle","scan","sharp"],"ScanOutline":["outline","scan"],"ScanSharp":["scan","sharp"],"School":["school"],"SchoolOutline":["outline","school"],"SchoolSharp":["school","sharp"],"Search":["glass","magnifying","search"],"SearchCircle":["circle","glass","magnifying","search"],"SearchCircleOutline":["circle","glass","magnifying","outline","search"],"SearchCircleSharp":["circle","glass","magnifying","search","sharp"],"SearchOutline":["glass","magnifying","outline","search"],"SearchSharp":["glass","magnifying","search","sharp"],"Send":["email","paper","send"],"SendOutline":["email","outline","paper","send"],"SendSharp":["email","paper","send","sharp"],"Server":["server"],"ServerOutline":["outline","server"],"ServerSharp":["server","sharp"],"Settings":["options","settings"],"SettingsOutline":["options","outline","settings"],"SettingsSharp":["options","settings","sharp"],"Shapes":["shapes"],"ShapesOutline":["outline","shapes"],"ShapesSharp":["shapes","sharp"],"Share":["share"],"ShareOutline":["outline","share"],"ShareSharp":["share","sharp"],"ShareSocial":["share","social"],"ShareSocialOutline":["outline","share","social"],"ShareSocialSharp":["share","sharp","social"],"Shield":["shield"],"ShieldCheckmark":["checkmark","shield"],"ShieldCheckmarkOutline":["checkmark","outline","shield"],"ShieldCheckmarkSharp":["checkmark","sharp","shield"],"ShieldOutline":["outline","shield"],"ShieldSharp":["sharp","shield"],"Shirt":["shirt"],"ShirtOutline":["outline","shirt"],"ShirtSharp":["sharp","shirt"],"Shuffle":["random","shuffle"],"ShuffleOutline":["outline","shuffle"],"ShuffleSharp":["random","sharp","shuffle"],"Skull":["skull"],"SkullOutline":["outline","skull"],"SkullSharp":["sharp","skull"],"Snow":["cold","snow"],"SnowOutline":["cold","outline","snow"],"SnowSharp":["cold","sharp","snow"],"Speedometer":["drive","level","speed","speedometer"],"SpeedometerOutline":["drive","level","outline","speed","speedometer"],"SpeedometerSharp":["drive","level","sharp","speed","speedometer"],"Square":["square"],"SquareOutline":["outline","square"],"SquareSharp":["sharp","square"],"Star":["favorite","star"],"StarHalf":["favorite","half","rate","star"],"StarHalfOutline":["half","outline","star"],"StarHalfSharp":["favorite","half","rate","sharp","star"],"StarOutline":["favorite","outline","star"],"StarSharp":["favorite","sharp","star"],"StatsChart":["chart","stats"],"StatsChartOutline":["chart","outline","stats"],"StatsChartSharp":["chart","sharp","stats"],"Stop":["stop"],"StopCircle":["circle","stop"],"StopCircleOutline":["circle","outline","stop"],"StopCircleSharp":["circle","sharp","stop"],"StopOutline":["outline","stop"],"StopSharp":["sharp","stop"],"Stopwatch":["stopwatch","time"],"StopwatchOutline":["outline","stopwatch","time"],"StopwatchSharp":["sharp","stopwatch","time"],"Subway":["subway"],"SubwayOutline":["outline","subway"],"SubwaySharp":["sharp","subway"],"Sunny":["light","sky","sunny","weather","whether"],"SunnyOutline":["light","outline","sky","sunny","weather","whether"],"SunnySharp":["light","sharp","sky","sunny","weather","whether"],"SwapHorizontal":["horizontal","swap"],"SwapHorizontalOutline":["horizontal","outline","swap"],"SwapHorizontalSharp":["horizontal","sharp","swap"],"SwapVertical":["swap","vertical"],"SwapVerticalOutline":["outline","swap","vertical"],"SwapVerticalSharp":["sharp","swap","vertical"],"Sync":["sync"],"SyncCircle":["circle","sync"],"SyncCircleOutline":["circle","outline","sync"],"SyncCircleSharp":["circle","sharp","sync"],"SyncOutline":["outline","sync"],"SyncSharp":["sharp","sync"],"TabletLandscape":["landscape","tablet"],"TabletLandscapeOutline":["landscape","outline","tablet"],"TabletLandscapeSharp":["landscape","sharp","tablet"],"TabletPortrait":["portrait","tablet"],"TabletPortraitOutline":["outline","portrait","tablet"],"TabletPortraitSharp":["portrait","sharp","tablet"],"Tennisball":["tennisball"],"TennisballOutline":["outline","tennisball"],"TennisballSharp":["sharp","tennisball"],"Terminal":["terminal"],"TerminalOutline":["outline","terminal"],"TerminalSharp":["sharp","terminal"],"Text":["text"],"TextOutline":["outline","text"],"TextSharp":["sharp","text"],"Thermometer":["cold","heat","hot","mercury","temperature","thermometer"],"ThermometerOutline":["cold","heat","hot","mercury","outline","temperature","thermometer"],"ThermometerSharp":["cold","heat","hot","mercury","sharp","temperature","thermometer"],"ThumbsDown":["down","thumbs"],"ThumbsDownOutline":["down","outline","thumbs"],"ThumbsDownSharp":["down","sharp","thumbs"],"ThumbsUp":["thumbs","up"],"ThumbsUpOutline":["outline","thumbs","up"],"ThumbsUpSharp":["sharp","thumbs","up"],"Thunderstorm":["cloudy","lightning","overcast","rain","sky","storm","thunderstorm","weather","whether"],"ThunderstormOutline":["cloudy","lightning","outline","overcast","rain","sky","storm","thunderstorm","weather","whether"],"ThunderstormSharp":["cloudy","lightning","overcast","rain","sharp","sky","storm","thunderstorm","weather","whether"],"Time":["clock","hour","minute","second","time","watch"],"TimeOutline":["clock","hour","minute","outline","second","time","watch"],"TimeSharp":["clock","hour","minute","second","sharp","time","watch"],"Timer":["clock","timer"],"TimerOutline":["clock","outline","timer"],"TimerSharp":["clock","sharp","timer"],"Today":["today"],"TodayOutline":["outline","today"],"TodaySharp":["sharp","today"],"Toggle":["switch","toggle"],"ToggleOutline":["outline","switch","toggle"],"ToggleSharp":["sharp","switch","toggle"],"TrailSign":["sign","trail"],"TrailSignOutline":["outline","sign","trail"],"TrailSignSharp":["sharp","sign","trail"],"Train":["train"],"TrainOutline":["outline","train"],"TrainSharp":["sharp","train"],"Transgender":["transgender"],"TransgenderOutline":["outline","transgender"],"TransgenderSharp":["sharp","transgender"],"Trash":["close","delete","remove","trash"],"TrashBin":["bin","trash"],"TrashBinOutline":["bin","outline","trash"],"TrashBinSharp":["bin","sharp","trash"],"TrashOutline":["close","delete","outline","remove","trash"],"TrashSharp":["close","delete","remove","sharp","trash"],"TrendingDown":["down","trending"],"TrendingDownOutline":["down","outline","trending"],"TrendingDownSharp":["down","sharp","trending"],"TrendingUp":["trending","up"],"TrendingUpOutline":["outline","trending","up"],"TrendingUpSharp":["sharp","trending","up"],"Triangle":["triangle"],"TriangleOutline":["outline","triangle"],"TriangleSharp":["sharp","triangle"],"Trophy":["award","compete","competition","lose","trophy","win"],"TrophyOutline":["award","compete","competition","lose","outline","trophy","win"],"TrophySharp":["award","compete","competition","lose","sharp","trophy","win"],"Tv":["television","tv"],"TvOutline":["outline","television","tv"],"TvSharp":["sharp","television","tv"],"Umbrella":["dry","rain","shelter","umbrella","wet"],"UmbrellaOutline":["dry","outline","rain","shelter","umbrella","wet"],"UmbrellaSharp":["dry","rain","sharp","shelter","umbrella","wet"],"Videocam":["camera","film","movie","videocam"],"VideocamOutline":["camera","film","movie","outline","videocam"],"VideocamSharp":["camera","film","movie","sharp","videocam"],"VolumeHigh":["high","volume"],"VolumeHighOutline":["high","outline","volume"],"VolumeHighSharp":["high","sharp","volume"],"VolumeLow":["low","volume"],"VolumeLowOutline":["low","outline","volume"],"VolumeLowSharp":["low","sharp","volume"],"VolumeMedium":["medium","volume"],"VolumeMediumOutline":["medium","outline","volume"],"VolumeMediumSharp":["medium","sharp","volume"],"VolumeMute":["mute","sound","volume"],"VolumeMuteOutline":["mute","outline","sound","volume"],"VolumeMuteSharp":["mute","sharp","sound","volume"],"VolumeOff":["off","volume"],"VolumeOffOutline":["off","outline","volume"],"VolumeOffSharp":["off","sharp","volume"],"Walk":["walk"],"WalkOutline":["outline","walk"],"WalkSharp":["sharp","walk"],"Wallet":["cash","money","wallet"],"WalletOutline":["cash","money","outline","wallet"],"WalletSharp":["cash","money","sharp","wallet"],"Warning":["warning"],"WarningOutline":["outline","warning"],"WarningSharp":["sharp","warning"],"Watch":["watch"],"WatchOutline":["outline","watch"],"WatchSharp":["sharp","watch"],"Water":["water"],"WaterOutline":["outline","water"],"WaterSharp":["sharp","water"],"Wifi":["bars","connection","internet","wifi"],"WifiOutline":["bars","connection","internet","outline","wifi"],"WifiSharp":["bars","connection","internet","sharp","wifi"],"Wine":["glass","wine"],"WineOutline":["glass","outline","wine"],"WineSharp":["glass","sharp","wine"],"Woman":["dudette","female","girl","lady","woman"],"WomanOutline":["dudette","female","girl","lady","outline","woman"],"WomanSharp":["dudette","female","girl","lady","sharp","woman"]}